[{"year":1995,"Malay":45.1,"Chinese":73.3,"Indian":50.1,"Overall":67.7},{"year":1996,"Malay":49.8,"Chinese":76.8,"Indian":54,"Overall":71.3},{"year":1997,"Malay":54.5,"Chinese":78.2,"Indian":58.7,"Overall":72.9},{"year":1998,"Malay":62.6,"Chinese":81,"Indian":61.1,"Overall":76.3},{"year":1999,"Malay":66.4,"Chinese":82.4,"Indian":64.6,"Overall":78.2},{"year":2000,"Malay":70,"Chinese":88.4,"Indian":74.9,"Overall":83.8},{"year":2001,"Malay":74.6,"Chinese":90.2,"Indian":77.7,"Overall":86.2},{"year":2002,"Malay":76.2,"Chinese":91.4,"Indian":80.1,"Overall":87.6},{"year":2003,"Malay":78.4,"Chinese":91.6,"Indian":82,"Overall":88},{"year":2004,"Malay":79,"Chinese":92.9,"Indian":85.1,"Overall":89.5},{"year":2005,"Malay":81.7,"Chinese":93.6,"Indian":84.7,"Overall":90.9},{"year":2006,"Malay":82.9,"Chinese":93.6,"Indian":86.6,"Overall":90.8},{"year":2007,"Malay":84.1,"Chinese":94.3,"Indian":87.6,"Overall":91.8},{"year":2008,"Malay":86,"Chinese":95.6,"Indian":90.2,"Overall":93.2},{"year":2009,"Malay":87.2,"Chinese":95.8,"Indian":90.5,"Overall":93.7},{"year":2010,"Malay":88.3,"Chinese":96.5,"Indian":92.2,"Overall":94.5},{"year":2011,"Malay":89.3,"Chinese":96.9,"Indian":92.8,"Overall":95.1},{"year":2012,"Malay":89.9,"Chinese":97.3,"Indian":93.8,"Overall":95.6}]